[
    {
      "area_name": "Alabama",
      "average_unemployment_rate": 3.661250474268002,
      "employment": 2218625,
      "forecasted_unemployment_rate": 2.6479248870344647,
      "industry_employment": 16955,
      "labor_force": 2276358,
      "unemployment_rate": 2.5362003691862176
    },
    {
      "area_name": "Alaska",
      "average_unemployment_rate": 3.661250474268002,
      "employment": 338730,
      "forecasted_unemployment_rate": 4.71985512819063,
      "industry_employment": 11545,
      "labor_force": 353692,
      "unemployment_rate": 4.230234215079787
    },
    {
      "area_name": "Arizona",
      "average_unemployment_rate": 3.661250474268002,
      "employment": 3462672,
      "forecasted_unemployment_rate": 3.9311093584136376,
      "industry_employment": 30950,
      "labor_force": 3599531,
      "unemployment_rate": 3.8021342224862074
    },
    {
      "area_name": "Arkansas",
      "average_unemployment_rate": 3.661250474268002,
      "employment": 1315890,
      "forecasted_unemployment_rate": 3.376777983238529,
      "industry_employment": 15019,
      "labor_force": 1359546,
      "unemployment_rate": 3.2110719313653235
    },
    {
      "area_name": "California",
      "average_unemployment_rate": 3.661250474268002,
      "employment": 18348918,
      "forecasted_unemployment_rate": 4.620213679705797,
      "industry_employment": 434918,
      "labor_force": 19169345,
      "unemployment_rate": 4.2798906274575375
    },
    {
      "area_name": "Colorado",
      "average_unemployment_rate": 3.661250474268002,
      "employment": 3089083,
      "forecasted_unemployment_rate": 3.253265435412827,
      "industry_employment": 38811,
      "labor_force": 3186941,
      "unemployment_rate": 3.0705933997523016
    },
    {
      "area_name": "Connecticut",
      "average_unemployment_rate": 3.661250474268002,
      "employment": 1833670,
      "forecasted_unemployment_rate": 4.1315766488791095,
      "industry_employment": 4368,
      "labor_force": 1912011,
      "unemployment_rate": 4.097309063598484
    },
    {
      "area_name": "Delaware",
      "average_unemployment_rate": 3.661250474268002,
      "employment": 475994,
      "forecasted_unemployment_rate": 4.287511489317196,
      "industry_employment": 737,
      "labor_force": 497201,
      "unemployment_rate": 4.265277020762227
    },
    {
      "area_name": "District of Columbia",
      "average_unemployment_rate": 3.661250474268002,
      "employment": 369952,
      "forecasted_unemployment_rate": 4.746979172835348,
      "industry_employment": 11,
      "labor_force": 388387,
      "unemployment_rate": 4.746554338842444
    },
    {
      "area_name": "Florida",
      "average_unemployment_rate": 3.661250474268002,
      "employment": 10370751,
      "forecasted_unemployment_rate": 3.107093171320926,
      "industry_employment": 71881,
      "labor_force": 10692185,
      "unemployment_rate": 3.006251762385331
    },
    {
      "area_name": "Georgia",
      "average_unemployment_rate": 3.661250474268002,
      "employment": 5058175,
      "forecasted_unemployment_rate": 3.2218363967775696,
      "industry_employment": 27649,
      "labor_force": 5222281,
      "unemployment_rate": 3.1424199502094967
    },
    {
      "area_name": "Hawaii",
      "average_unemployment_rate": 3.661250474268002,
      "employment": 566402,
      "forecasted_unemployment_rate": 3.422152212147606,
      "industry_employment": 5421,
      "labor_force": 585630,
      "unemployment_rate": 3.2833017434216143
    },
    {
      "area_name": "Idaho",
      "average_unemployment_rate": 3.661250474268002,
      "employment": 918107,
      "forecasted_unemployment_rate": 3.2595423321103008,
      "industry_employment": 26574,
      "labor_force": 944921,
      "unemployment_rate": 2.8376975429692006
    },
    {
      "area_name": "Illinois",
      "average_unemployment_rate": 3.661250474268002,
      "employment": 6127488,
      "forecasted_unemployment_rate": 4.641686562673821,
      "industry_employment": 25602,
      "labor_force": 6421724,
      "unemployment_rate": 4.581884864562849
    },
    {
      "area_name": "Indiana",
      "average_unemployment_rate": 3.661250474268002,
      "employment": 3270670,
      "forecasted_unemployment_rate": 3.1527620606930773,
      "industry_employment": 20979,
      "labor_force": 3373894,
      "unemployment_rate": 3.0594914955834414
    },
    {
      "area_name": "Iowa",
      "average_unemployment_rate": 3.661250474268002,
      "employment": 1658263,
      "forecasted_unemployment_rate": 3.0223979429192975,
      "industry_employment": 22294,
      "labor_force": 1706496,
      "unemployment_rate": 2.826434987248725
    },
    {
      "area_name": "Kansas",
      "average_unemployment_rate": 3.661250474268002,
      "employment": 1463011,
      "forecasted_unemployment_rate": 2.8190242944752644,
      "industry_employment": 18432,
      "labor_force": 1502605,
      "unemployment_rate": 2.6350238419278518
    },
    {
      "area_name": "Kentucky",
      "average_unemployment_rate": 3.661250474268002,
      "employment": 1948314,
      "forecasted_unemployment_rate": 4.15402225705051,
      "industry_employment": 15828,
      "labor_force": 2030278,
      "unemployment_rate": 4.037082606421387
    },
    {
      "area_name": "Louisiana",
      "average_unemployment_rate": 3.661250474268002,
      "employment": 1993247,
      "forecasted_unemployment_rate": 3.918119143106972,
      "industry_employment": 36553,
      "labor_force": 2068823,
      "unemployment_rate": 3.6530916371289375
    },
    {
      "area_name": "Maine",
      "average_unemployment_rate": 3.661250474268002,
      "employment": 661832,
      "forecasted_unemployment_rate": 3.0277345923417243,
      "industry_employment": 8567,
      "labor_force": 681171,
      "unemployment_rate": 2.8390815228481543
    },
    {
      "area_name": "Maryland",
      "average_unemployment_rate": 3.661250474268002,
      "employment": 3060217,
      "forecasted_unemployment_rate": 3.0281467591082634,
      "industry_employment": 5958,
      "labor_force": 3154857,
      "unemployment_rate": 2.9998190092292614
    },
    {
      "area_name": "Massachusetts",
      "average_unemployment_rate": 3.661250474268002,
      "employment": 3606318,
      "forecasted_unemployment_rate": 3.7219927930141896,
      "industry_employment": 13761,
      "labor_force": 3743590,
      "unemployment_rate": 3.666854543366127
    },
    {
      "area_name": "Michigan",
      "average_unemployment_rate": 3.661250474268002,
      "employment": 4664174,
      "forecasted_unemployment_rate": 4.269173220037274,
      "industry_employment": 38960,
      "labor_force": 4866071,
      "unemployment_rate": 4.149076328725989
    },
    {
      "area_name": "Minnesota",
      "average_unemployment_rate": 3.661250474268002,
      "employment": 2992787,
      "forecasted_unemployment_rate": 2.6997360207901506,
      "industry_employment": 28361,
      "labor_force": 3071454,
      "unemployment_rate": 2.5612299581891835
    },
    {
      "area_name": "Mississippi",
      "average_unemployment_rate": 3.661250474268002,
      "employment": 1200236,
      "forecasted_unemployment_rate": 4.006543561918669,
      "industry_employment": 14297,
      "labor_force": 1248097,
      "unemployment_rate": 3.8347179746445987
    },
    {
      "area_name": "Missouri",
      "average_unemployment_rate": 3.661250474268002,
      "employment": 2957356,
      "forecasted_unemployment_rate": 2.6917486191056534,
      "industry_employment": 16501,
      "labor_force": 3036619,
      "unemployment_rate": 2.6102385580805496
    },
    {
      "area_name": "Montana",
      "average_unemployment_rate": 3.661250474268002,
      "employment": 548850,
      "forecasted_unemployment_rate": 3.0033950589924823,
      "industry_employment": 11572,
      "labor_force": 564055,
      "unemployment_rate": 2.695659111256881
    },
    {
      "area_name": "Nebraska",
      "average_unemployment_rate": 3.661250474268002,
      "employment": 1027689,
      "forecasted_unemployment_rate": 2.3821202222833624,
      "industry_employment": 15594,
      "labor_force": 1050371,
      "unemployment_rate": 2.1594274784814127
    },
    {
      "area_name": "Nevada",
      "average_unemployment_rate": 3.661250474268002,
      "employment": 1476295,
      "forecasted_unemployment_rate": 5.378141198737036,
      "industry_employment": 16395,
      "labor_force": 1557606,
      "unemployment_rate": 5.220254672876196
    },
    {
      "area_name": "New Hampshire",
      "average_unemployment_rate": 3.661250474268002,
      "employment": 742976,
      "forecasted_unemployment_rate": 2.3367129928597135,
      "industry_employment": 2732,
      "labor_force": 760333,
      "unemployment_rate": 2.2828155558156755
    },
    {
      "area_name": "New Jersey",
      "average_unemployment_rate": 3.661250474268002,
      "employment": 4552564,
      "forecasted_unemployment_rate": 3.917393952766084,
      "industry_employment": 12568,
      "labor_force": 4736215,
      "unemployment_rate": 3.877590016500518
    },
    {
      "area_name": "New Mexico",
      "average_unemployment_rate": 3.661250474268002,
      "employment": 908879,
      "forecasted_unemployment_rate": 4.568223750596363,
      "industry_employment": 31646,
      "labor_force": 947412,
      "unemployment_rate": 4.067185131706164
    },
    {
      "area_name": "New York",
      "average_unemployment_rate": 3.661250474268002,
      "employment": 9178592,
      "forecasted_unemployment_rate": 4.3987626641633435,
      "industry_employment": 32730,
      "labor_force": 9595778,
      "unemployment_rate": 4.347599538046837
    },
    {
      "area_name": "North Carolina",
      "average_unemployment_rate": 3.661250474268002,
      "employment": 4965568,
      "forecasted_unemployment_rate": 3.772394064944877,
      "industry_employment": 27523,
      "labor_force": 5155942,
      "unemployment_rate": 3.692322372904893
    },
    {
      "area_name": "North Dakota",
      "average_unemployment_rate": 3.661250474268002,
      "employment": 403891,
      "forecasted_unemployment_rate": 2.7773869590529787,
      "industry_employment": 20670,
      "labor_force": 412240,
      "unemployment_rate": 2.0252765379390647
    },
    {
      "area_name": "Ohio",
      "average_unemployment_rate": 3.661250474268002,
      "employment": 5503271,
      "forecasted_unemployment_rate": 4.0766837532774405,
      "industry_employment": 25661,
      "labor_force": 5733144,
      "unemployment_rate": 4.009545198934476
    },
    {
      "area_name": "Oklahoma",
      "average_unemployment_rate": 3.661250474268002,
      "employment": 1845334,
      "forecasted_unemployment_rate": 3.3744765599184294,
      "industry_employment": 40364,
      "labor_force": 1903513,
      "unemployment_rate": 3.056401506057484
    },
    {
      "area_name": "Oregon",
      "average_unemployment_rate": 3.661250474268002,
      "employment": 2075082,
      "forecasted_unemployment_rate": 4.3323671081579604,
      "industry_employment": 58047,
      "labor_force": 2159952,
      "unemployment_rate": 3.929253983421854
    },
    {
      "area_name": "Pennsylvania",
      "average_unemployment_rate": 3.661250474268002,
      "employment": 6202050,
      "forecasted_unemployment_rate": 4.18007912445258,
      "industry_employment": 46966,
      "labor_force": 6465258,
      "unemployment_rate": 4.071113635372324
    },
    {
      "area_name": "Rhode Island",
      "average_unemployment_rate": 3.661250474268002,
      "employment": 553588,
      "forecasted_unemployment_rate": 3.2103467213286745,
      "industry_employment": 1249,
      "labor_force": 571756,
      "unemployment_rate": 3.177579247091417
    },
    {
      "area_name": "South Carolina",
      "average_unemployment_rate": 3.661250474268002,
      "employment": 2316442,
      "forecasted_unemployment_rate": 3.287525623209095,
      "industry_employment": 11904,
      "labor_force": 2393338,
      "unemployment_rate": 3.2129185263427065
    },
    {
      "area_name": "South Dakota",
      "average_unemployment_rate": 3.661250474268002,
      "employment": 464950,
      "forecasted_unemployment_rate": 2.2484031197907726,
      "industry_employment": 7334,
      "labor_force": 474519,
      "unemployment_rate": 2.0165683565884613
    },
    {
      "area_name": "Tennessee",
      "average_unemployment_rate": 3.661250474268002,
      "employment": 3247978,
      "forecasted_unemployment_rate": 3.4404207987716786,
      "industry_employment": 11050,
      "labor_force": 3361987,
      "unemployment_rate": 3.3911195968336583
    },
    {
      "area_name": "Texas",
      "average_unemployment_rate": 3.661250474268002,
      "employment": 14093923,
      "forecasted_unemployment_rate": 4.195453893330549,
      "industry_employment": 247727,
      "labor_force": 14672335,
      "unemployment_rate": 3.9421946131955137
    },
    {
      "area_name": "Utah",
      "average_unemployment_rate": 3.661250474268002,
      "employment": 1696513,
      "forecasted_unemployment_rate": 2.511081916119841,
      "industry_employment": 16054,
      "labor_force": 1737741,
      "unemployment_rate": 2.3725054539197727
    },
    {
      "area_name": "Vermont",
      "average_unemployment_rate": 3.661250474268002,
      "employment": 335548,
      "forecasted_unemployment_rate": 2.508725051011349,
      "industry_employment": 4105,
      "labor_force": 343551,
      "unemployment_rate": 2.3294940198107414
    },
    {
      "area_name": "Virginia",
      "average_unemployment_rate": 3.661250474268002,
      "employment": 2534014,
      "forecasted_unemployment_rate": 2.917347089834267,
      "industry_employment": 17575,
      "labor_force": 2607446,
      "unemployment_rate": 2.816242407321187
    },
    {
      "area_name": "Washington",
      "average_unemployment_rate": 3.661250474268002,
      "employment": 3806849,
      "forecasted_unemployment_rate": 4.472730405335456,
      "industry_employment": 96294,
      "labor_force": 3969971,
      "unemployment_rate": 4.108896513349846
    },
    {
      "area_name": "West Virginia",
      "average_unemployment_rate": 3.661250474268002,
      "employment": 748271,
      "forecasted_unemployment_rate": 4.285207953163511,
      "industry_employment": 19542,
      "labor_force": 778709,
      "unemployment_rate": 3.9087772197316326
    },
    {
      "area_name": "Wisconsin",
      "average_unemployment_rate": 3.661250474268002,
      "employment": 3004781,
      "forecasted_unemployment_rate": 3.0660387264954587,
      "industry_employment": 31250,
      "labor_force": 3094987,
      "unemployment_rate": 2.914584132340459
    },
    {
      "area_name": "Wyoming",
      "average_unemployment_rate": 3.661250474268002,
      "employment": 282615,
      "forecasted_unemployment_rate": 4.385538998780159,
      "industry_employment": 18579,
      "labor_force": 292663,
      "unemployment_rate": 3.4333004172034047
    }
  ]